{
  "generatedAt": "2026-03-28T05:35:46Z",
  "topic": "kotlin",
  "totalCount": 4,
  "repos": [
    {
      "id": "1188370478",
      "name": "proxy-turn-vk-android",
      "nameWithOwner": "amurcanov/proxy-turn-vk-android",
      "description": "WireGuard‑туннель через DTLS‑медиарелей ВК TURN‑серверов: трафик проходит от клиента к вашему личному VPS‑серверу через промежуточные медиарелей‑серверы ВК.",
      "url": "https://github.com/amurcanov/proxy-turn-vk-android",
      "stargazerCount": 38,
      "forkCount": 0,
      "languageName": "Kotlin",
      "languageColor": null,
      "ownerLogin": "amurcanov",
      "ownerAvatarUrl": "https://avatars.githubusercontent.com/u/222097921?v=4",
      "ownerType": "User",
      "createdAt": "2026-03-22T01:23:43Z",
      "updatedAt": "2026-03-28T03:48:28Z",
      "licenseName": "GPL-3.0",
      "topics": [
        "android",
        "android-application",
        "calls",
        "dpi",
        "dpi-bypass",
        "dtls",
        "golang",
        "kotlin",
        "proxy-turn-vk-android",
        "shell",
        "turn",
        "vk-api",
        "vk-tunnel",
        "vkontakte",
        "vpn",
        "wdtt",
        "whitelist",
        "whitelist-bypass",
        "wireguard"
      ],
      "openIssuesCount": 1,
      "closedIssuesCount": 0
    },
    {
      "id": "1188629287",
      "name": "CatPawSwitch",
      "nameWithOwner": "hearsilent/CatPawSwitch",
      "description": "A MaterialSwitch that proactively tries to turn itself off using a cat's paw animation.",
      "url": "https://github.com/hearsilent/CatPawSwitch",
      "stargazerCount": 13,
      "forkCount": 1,
      "languageName": "Kotlin",
      "languageColor": null,
      "ownerLogin": "hearsilent",
      "ownerAvatarUrl": "https://avatars.githubusercontent.com/u/5742579?v=4",
      "ownerType": "User",
      "createdAt": "2026-03-22T11:09:41Z",
      "updatedAt": "2026-03-27T15:27:38Z",
      "licenseName": "MIT",
      "topics": [
        "android",
        "android-library",
        "kotlin",
        "kotlin-library",
        "material-design",
        "material-ui"
      ],
      "openIssuesCount": 0,
      "closedIssuesCount": 0
    },
    {
      "id": "1188980366",
      "name": "crypto",
      "nameWithOwner": "ic-timon/crypto",
      "description": "🚀 A focused, high-performance Android Cryptographic SDK (AAR).",
      "url": "https://github.com/ic-timon/crypto",
      "stargazerCount": 8,
      "forkCount": 0,
      "languageName": "Kotlin",
      "languageColor": null,
      "ownerLogin": "ic-timon",
      "ownerAvatarUrl": "https://avatars.githubusercontent.com/u/23233894?v=4",
      "ownerType": "User",
      "createdAt": "2026-03-22T20:50:18Z",
      "updatedAt": "2026-03-28T03:47:53Z",
      "licenseName": "MIT",
      "topics": [
        "android",
        "crypto",
        "golang",
        "kotlin",
        "ndk"
      ],
      "openIssuesCount": 0,
      "closedIssuesCount": 0
    },
    {
      "id": "1191069547",
      "name": "WhatsApp-agent",
      "nameWithOwner": "iamEtornam/WhatsApp-agent",
      "description": "WhatsApp bot powered by Google Gemini 3 Flash Preview and the Koog AI agent framework. ",
      "url": "https://github.com/iamEtornam/WhatsApp-agent",
      "stargazerCount": 8,
      "forkCount": 0,
      "languageName": "Kotlin",
      "languageColor": null,
      "ownerLogin": "iamEtornam",
      "ownerAvatarUrl": "https://avatars.githubusercontent.com/u/19475061?v=4",
      "ownerType": "User",
      "createdAt": "2026-03-24T22:22:10Z",
      "updatedAt": "2026-03-27T23:00:18Z",
      "licenseName": "MIT",
      "topics": [
        "gemini",
        "ghana",
        "koog",
        "kotlin",
        "whatsapp-bot"
      ],
      "openIssuesCount": 0,
      "closedIssuesCount": 0
    }
  ]
}