{
  "generatedAt": "2026-05-07T06:51:00Z",
  "period": "daily",
  "totalCount": 7,
  "repos": [
    {
      "id": "1231424857",
      "name": "Bertex-Here",
      "nameWithOwner": "BertecKol/Bertex-Here",
      "description": null,
      "url": "https://github.com/BertecKol/Bertex-Here",
      "stargazerCount": 47,
      "forkCount": 0,
      "languageName": null,
      "languageColor": null,
      "ownerLogin": "BertecKol",
      "ownerAvatarUrl": "https://avatars.githubusercontent.com/u/282040680?v=4",
      "ownerType": "User",
      "createdAt": "2026-05-07T00:28:14Z",
      "updatedAt": "2026-05-07T00:53:33Z",
      "licenseName": null,
      "topics": [
        "bitcoin-flash-transactions",
        "btc-flash-payments",
        "fake-btc-transaction",
        "flash-btc-btc-fake",
        "flash-btc-transfer",
        "flash-uadt-sender-ios",
        "flash-usdt-fake-sender",
        "flash-usdt-online-sender",
        "flash-usdt-sender-app",
        "flash-usdt-sender-software-generator",
        "flashcrypto",
        "usdt-flash-crypto",
        "usdt-online-sender"
      ],
      "openIssuesCount": 0,
      "closedIssuesCount": 0
    },
    {
      "id": "1231420405",
      "name": "front-1sem-aula-07",
      "nameWithOwner": "1TDSPO-26/front-1sem-aula-07",
      "description": null,
      "url": "https://github.com/1TDSPO-26/front-1sem-aula-07",
      "stargazerCount": 21,
      "forkCount": 0,
      "languageName": "HTML",
      "languageColor": null,
      "ownerLogin": "1TDSPO-26",
      "ownerAvatarUrl": "https://avatars.githubusercontent.com/u/276447020?v=4",
      "ownerType": "Organization",
      "createdAt": "2026-05-07T00:18:30Z",
      "updatedAt": "2026-05-07T02:08:36Z",
      "licenseName": null,
      "topics": [],
      "openIssuesCount": 0,
      "closedIssuesCount": 0
    },
    {
      "id": "1231442254",
      "name": "Natural-Language-Hardware-Development",
      "nameWithOwner": "ailyProject/Natural-Language-Hardware-Development",
      "description": "未来，大部分人都将使用自然语言进行硬件开发，而本书则是为了让新时代开发者进行项目开发所写",
      "url": "https://github.com/ailyProject/Natural-Language-Hardware-Development",
      "stargazerCount": 10,
      "forkCount": 2,
      "languageName": null,
      "languageColor": null,
      "ownerLogin": "ailyProject",
      "ownerAvatarUrl": "https://avatars.githubusercontent.com/u/158834988?v=4",
      "ownerType": "Organization",
      "createdAt": "2026-05-07T01:02:05Z",
      "updatedAt": "2026-05-07T03:18:19Z",
      "licenseName": null,
      "topics": [],
      "openIssuesCount": 0,
      "closedIssuesCount": 0
    },
    {
      "id": "1231453712",
      "name": "cvcl",
      "nameWithOwner": "kavishka-dot/cvcl",
      "description": "High-performance computer vision primitives in pure C99. Zero dependencies, pluggable allocator, SIMD-ready layout. Built for edge deployment and FFI.",
      "url": "https://github.com/kavishka-dot/cvcl",
      "stargazerCount": 8,
      "forkCount": 0,
      "languageName": "C",
      "languageColor": null,
      "ownerLogin": "kavishka-dot",
      "ownerAvatarUrl": "https://avatars.githubusercontent.com/u/82282978?v=4",
      "ownerType": "User",
      "createdAt": "2026-05-07T01:23:15Z",
      "updatedAt": "2026-05-07T05:57:51Z",
      "licenseName": "NOASSERTION",
      "topics": [
        "c",
        "c99",
        "computer-vision",
        "edge-computing",
        "embedded",
        "high-performance",
        "image-processing",
        "library",
        "signal-processing",
        "simd"
      ],
      "openIssuesCount": 0,
      "closedIssuesCount": 0
    },
    {
      "id": "1231476691",
      "name": "FingerScan",
      "nameWithOwner": "TD0U/FingerScan",
      "description": "BurpSuite 被动指纹识别 / Favicon Hash / 递归目录扫描 / 路径收集 一体化插件",
      "url": "https://github.com/TD0U/FingerScan",
      "stargazerCount": 8,
      "forkCount": 0,
      "languageName": "Java",
      "languageColor": null,
      "ownerLogin": "TD0U",
      "ownerAvatarUrl": "https://avatars.githubusercontent.com/u/75050574?v=4",
      "ownerType": "User",
      "createdAt": "2026-05-07T02:05:03Z",
      "updatedAt": "2026-05-07T06:30:30Z",
      "licenseName": "GPL-3.0",
      "topics": [
        "burp-extension",
        "burpsuite",
        "fingerprint",
        "java",
        "security-tools"
      ],
      "openIssuesCount": 0,
      "closedIssuesCount": 0
    },
    {
      "id": "1231531304",
      "name": "vmpstatic",
      "nameWithOwner": "meridi4n/vmpstatic",
      "description": "PE tool for vmprotect binaries",
      "url": "https://github.com/meridi4n/vmpstatic",
      "stargazerCount": 7,
      "forkCount": 2,
      "languageName": "C",
      "languageColor": null,
      "ownerLogin": "meridi4n",
      "ownerAvatarUrl": "https://avatars.githubusercontent.com/u/282032199?v=4",
      "ownerType": "User",
      "createdAt": "2026-05-07T03:40:28Z",
      "updatedAt": "2026-05-07T03:48:58Z",
      "licenseName": null,
      "topics": [],
      "openIssuesCount": 0,
      "closedIssuesCount": 0
    },
    {
      "id": "1231489770",
      "name": "skill_sony",
      "nameWithOwner": "xll0328/skill_sony",
      "description": null,
      "url": "https://github.com/xll0328/skill_sony",
      "stargazerCount": 6,
      "forkCount": 1,
      "languageName": "TeX",
      "languageColor": null,
      "ownerLogin": "xll0328",
      "ownerAvatarUrl": "https://avatars.githubusercontent.com/u/126251921?v=4",
      "ownerType": "User",
      "createdAt": "2026-05-07T02:28:17Z",
      "updatedAt": "2026-05-07T03:54:00Z",
      "licenseName": null,
      "topics": [],
      "openIssuesCount": 0,
      "closedIssuesCount": 0
    }
  ]
}